redlink/__init__.py
redlink/admin.py
redlink/app_settings.py
redlink/apps.py
redlink/errors.py
redlink/models.py
redlink/notification.py
redlink/redlink_client.py
redlink/serializers.py
redlink/utils.py
redlink/views.py
redlink/migrations/0001_initial.py
redlink/migrations/0002_delete_devicenotificationsettings.py
redlink/migrations/0003_sentpush.py
redlink/migrations/0004_body.py
redlink/migrations/__init__.py
redlink/tests/__init__.py
redlink/tests/factories.py
redlink/tests/test_models.py
redlink/tests/test_redlink_client.py
redlink/tests/test_serializers.py
appchance_redlink-0.0.6.dist-info/METADATA
appchance_redlink-0.0.6.dist-info/WHEEL
appchance_redlink-0.0.6.dist-info/top_level.txt
appchance_redlink-0.0.6.dist-info/RECORD
