Metadata-Version: 2.1
Name: appchance-redlink
Version: 0.0.6
Summary: Redlink extensions for Django projects.
Home-page: https://bitbucket.org/appchance/appchance-redlink/
Author-email: backend@appchance.com
License: UNKNOWN
Platform: UNKNOWN
Classifier: Programming Language :: Python :: 3.8
Classifier: Operating System :: POSIX :: Linux
Requires-Python: >=3.8
Requires-Dist: django
Requires-Dist: swapper
